pixellib/__init__.py
pixellib/custom_train/__init__.py
pixellib/instance/__init__.py
pixellib/instance/config.py
pixellib/instance/mask_rcnn.py
pixellib/instance/utils.py
pixellib/semantic/__init__.py
pixellib/semantic/deeplab.py
pixellib/torchbackend/__init__.py
pixellib/torchbackend/instance/__init__.py
pixellib/torchbackend/instance/checkpoint/__init__.py
pixellib/torchbackend/instance/checkpoint/c2_model_loading.py
pixellib/torchbackend/instance/checkpoint/catalog.py
pixellib/torchbackend/instance/checkpoint/detection_checkpoint.py
pixellib/torchbackend/instance/config/__init__.py
pixellib/torchbackend/instance/config/compat.py
pixellib/torchbackend/instance/config/config.py
pixellib/torchbackend/instance/config/defaults.py
pixellib/torchbackend/instance/config/instantiate.py
pixellib/torchbackend/instance/config/lazy.py
pixellib/torchbackend/instance/data/__init__.py
pixellib/torchbackend/instance/data/benchmark.py
pixellib/torchbackend/instance/data/build_data.py
pixellib/torchbackend/instance/data/catalogdata.py
pixellib/torchbackend/instance/data/common.py
pixellib/torchbackend/instance/data/dataset_mapper.py
pixellib/torchbackend/instance/data/detection_utils.py
pixellib/torchbackend/instance/data/datasets/__init__.py
pixellib/torchbackend/instance/data/datasets/builtin_meta.py
pixellib/torchbackend/instance/data/datasets/coco.py
pixellib/torchbackend/instance/data/datasets/register_coco.py
pixellib/torchbackend/instance/data/samplers/__init__.py
pixellib/torchbackend/instance/data/samplers/distributed_sampler.py
pixellib/torchbackend/instance/data/samplers/grouped_batch_sampler.py
pixellib/torchbackend/instance/data/transforms/__init__.py
pixellib/torchbackend/instance/data/transforms/augmentation.py
pixellib/torchbackend/instance/data/transforms/augmentation_impl.py
pixellib/torchbackend/instance/data/transforms/transform.py
pixellib/torchbackend/instance/engine/__init__.py
pixellib/torchbackend/instance/engine/defaultseng.py
pixellib-0.7.0.dist-info/LICENSE
pixellib-0.7.0.dist-info/METADATA
pixellib-0.7.0.dist-info/WHEEL
pixellib-0.7.0.dist-info/top_level.txt
pixellib-0.7.0.dist-info/RECORD
