Metadata-Version: 2.1
Name: pixellib
Version: 0.7.0
Summary: PixelLib is a library used for easy implementation of semantic and instance segmentation of objects in images and videos with few lines of code.PixelLib makes it possible to train a custom segmentation model using few lines of code.PixelLib supports background editing of images and videos using few lines of code. 
Home-page: https://github.com/ayoolaolafenwa/PixelLib
Author: Ayoola Olafenwa
Author-email: UNKNOWN
License: MIT
Platform: UNKNOWN
Classifier: Programming Language :: Python :: 3
Classifier: License :: OSI Approved :: MIT License
Classifier: Operating System :: OS Independent
Requires-Dist: pillow
Requires-Dist: scikit-image
Requires-Dist: opencv-python
Requires-Dist: matplotlib
Requires-Dist: imgaug
Requires-Dist: labelme2coco
Requires-Dist: imantics
Requires-Dist: Cython
Requires-Dist: pyQt5
Requires-Dist: fvcore
Requires-Dist: iopath
Requires-Dist: omegaconf
Requires-Dist: cloudpickle
Requires-Dist: termcolor
Requires-Dist: yacs
Requires-Dist: tabulate
Requires-Dist: tqdm
Requires-Dist: future
Requires-Dist: pydot
Requires-Dist: dataclasses
Requires-Dist: hydra-core
Requires-Dist: black
